setup.py
Binomial_DS/Binomialdistribution.py
Binomial_DS/Gaussiandistribution.py
Binomial_DS/Generaldistribution.py
Binomial_DS/__init__.py
Binomial_DS.egg-info/PKG-INFO
Binomial_DS.egg-info/SOURCES.txt
Binomial_DS.egg-info/dependency_links.txt
Binomial_DS.egg-info/not-zip-safe
Binomial_DS.egg-info/top_level.txt